README.rst
netpie.py
setup.py
simple.py
micropython_netpie.egg-info/PKG-INFO
micropython_netpie.egg-info/SOURCES.txt
micropython_netpie.egg-info/dependency_links.txt
micropython_netpie.egg-info/top_level.txt
test/test_lib.py
test/test_lib2.py
test/test_netpie.py