Metadata-Version: 2.1
Name: micropython-netpie
Version: 1.0.0
Summary: MicroPython Library for Interfacing with the NETPIE IoT Platform
Home-page: https://github.com/PerfecXX/MicroPython-NETPIE
Author: Teeraphat Kullanankanjana
Author-email: ku.teeraphat@hotmail.com
Maintainer: Teeraphat Kullanankanjana
Maintainer-email: ku.teeraphat@hotmail.com
License: MIT
Keywords: NETPIE,esp32,esp8266,micropython
Platform: UNKNOWN
Classifier: Development Status :: 3 - Alpha
Classifier: Programming Language :: Python :: Implementation :: MicroPython
Classifier: License :: OSI Approved :: MIT License
